excel_tables/__init__.py
excel_tables/df_util.py
excel_tables/excel_util.py
excel_tables-0.5.4.dist-info/LICENCE
excel_tables-0.5.4.dist-info/METADATA
excel_tables-0.5.4.dist-info/WHEEL
excel_tables-0.5.4.dist-info/top_level.txt
excel_tables-0.5.4.dist-info/RECORD
