Metadata-Version: 2.1
Name: excel_tables
Version: 0.5.4
Summary: Python library to quickly export pandas tables to pretty, sensible Excel workbooks.
Author-email: Fralau <fralau@bluewin.ch>
License: MIT
Project-URL: Homepage, https://github.com/fralau/excel_tables
Requires-Python: >=3.6
License-File: LICENCE
Requires-Dist: pandas
Requires-Dist: pydantic
Requires-Dist: openpyxl
Requires-Dist: rich
Requires-Dist: babel
Requires-Dist: webcolors
Requires-Dist: pywin32; sys_platform == "win32"
Provides-Extra: tests
Requires-Dist: pytest; extra == "tests"
Requires-Dist: click; extra == "tests"
Requires-Dist: icecream; extra == "tests"
